{
  "$schema": "./registry.schema.json",
  "design_system_version": "0.1.0",
  "classification_enum": [
    "operations_dashboard",
    "ticket_action_queue",
    "data_table_app",
    "workflow_wizard",
    "executive_summary",
    "admin_configuration",
    "reporting_app",
    "intake_form_app",
    "TBD"
  ],
  "status_enum": [
    "not_started",
    "intake",
    "audited",
    "figma_current_captured",
    "target_designing",
    "target_approved",
    "implementing",
    "visual_qa",
    "adopted",
    "blocked"
  ],
  "apps": [
    {
      "id": "app-01",
      "name": "Vendor Escalation Tracker",
      "repo": "https://github.com/markheck-solutions/vendor-escalation-tracker.git",
      "local_path": "C:\\SoftwareFactory\\01-projects\\vendor-escalation-tracker",
      "stack": "Next.js App Router, React, TypeScript, Tailwind CSS, Drizzle ORM, Postgres/Supabase, Vitest, Playwright",
      "classification": "operations_dashboard",
      "current_ux_state": "Risk dashboard with priority queue, filters, read-only detail drawer, and mock draft generation.",
      "target_pattern": "Operations Dashboard + Table With Detail Drawer",
      "figma_current_state_url": "TBD",
      "figma_target_state_url": "TBD",
      "design_system_version": "0.1.0",
      "status": "intake",
      "priority": "P1",
      "notes": "Public demo is read-only with fictional data. Local repo currently has uncommitted work on codex/command-center-ux; do not alter app source without owner confirmation."
    },
    {
      "id": "app-02",
      "name": "Team Coverage and PTO Readiness Planner",
      "repo": "https://github.com/markheck-solutions/pto-readiness-planner.git",
      "local_path": "C:\\SoftwareFactory\\01-projects\\pto-readiness-planner",
      "stack": "Next.js App Router, React, TypeScript, Tailwind CSS, Postgres, Vitest, Playwright",
      "classification": "workflow_wizard",
      "current_ux_state": "PTO request decision support around coverage risk, role requirements, overlaps, delivery windows, and fairness context.",
      "target_pattern": "Workflow Wizard + Executive Summary",
      "figma_current_state_url": "TBD",
      "figma_target_state_url": "TBD",
      "design_system_version": "0.1.0",
      "status": "intake",
      "priority": "P2",
      "notes": "Decision support only, not an HR workflow. Local repo is on codex/architecture-gate-coverage."
    },
    {
      "id": "app-03",
      "name": "Migration Cutover Readiness Command Center",
      "repo": "https://github.com/markheck-solutions/migration-cutover-readiness.git",
      "local_path": "C:\\SoftwareFactory\\01-projects\\migration-cutover-readiness",
      "stack": "Next.js App Router, React, TypeScript, Tailwind CSS, Drizzle ORM, Postgres/PGlite, Sentry, PostHog, Vitest, Playwright",
      "classification": "operations_dashboard",
      "current_ux_state": "Read-only cutover readiness command center for wave go/no-go decisions, blockers, owners, and next actions.",
      "target_pattern": "Operations Dashboard + Blocker Panel",
      "figma_current_state_url": "TBD",
      "figma_target_state_url": "TBD",
      "design_system_version": "0.1.0",
      "status": "intake",
      "priority": "P3",
      "notes": "Public posture is read-only, static, fictional, with mock brief generation."
    },
    {
      "id": "app-04",
      "name": "Carrier Performance Intelligence Scorecard",
      "repo": "https://github.com/markheck-solutions/carrier-performance-scorecard.git",
      "local_path": "C:\\SoftwareFactory\\01-projects\\carrier-performance-scorecard",
      "stack": "Next.js App Router, React, TypeScript, Tailwind CSS, Drizzle ORM, Supabase/Postgres, Vitest, Playwright",
      "classification": "reporting_app",
      "current_ux_state": "Executive carrier health scorecard with deterministic scoring, explainable insights, and mock QBR brief generation.",
      "target_pattern": "Executive Summary + Reporting Page",
      "figma_current_state_url": "TBD",
      "figma_target_state_url": "TBD",
      "design_system_version": "0.1.0",
      "status": "intake",
      "priority": "P4",
      "notes": "Public demo is read-only with fictional telecom delivery data."
    },
    {
      "id": "app-05",
      "name": "TBD",
      "repo": "TBD",
      "local_path": "TBD",
      "stack": "TBD",
      "classification": "TBD",
      "current_ux_state": "TBD",
      "target_pattern": "TBD",
      "figma_current_state_url": "TBD",
      "figma_target_state_url": "TBD",
      "design_system_version": "0.1.0",
      "status": "not_started",
      "priority": "TBD",
      "notes": "TBD"
    },
    {
      "id": "app-06",
      "name": "TBD",
      "repo": "TBD",
      "local_path": "TBD",
      "stack": "TBD",
      "classification": "TBD",
      "current_ux_state": "TBD",
      "target_pattern": "TBD",
      "figma_current_state_url": "TBD",
      "figma_target_state_url": "TBD",
      "design_system_version": "0.1.0",
      "status": "not_started",
      "priority": "TBD",
      "notes": "TBD"
    },
    {
      "id": "app-07",
      "name": "TBD",
      "repo": "TBD",
      "local_path": "TBD",
      "stack": "TBD",
      "classification": "TBD",
      "current_ux_state": "TBD",
      "target_pattern": "TBD",
      "figma_current_state_url": "TBD",
      "figma_target_state_url": "TBD",
      "design_system_version": "0.1.0",
      "status": "not_started",
      "priority": "TBD",
      "notes": "TBD"
    },
    {
      "id": "app-08",
      "name": "TBD",
      "repo": "TBD",
      "local_path": "TBD",
      "stack": "TBD",
      "classification": "TBD",
      "current_ux_state": "TBD",
      "target_pattern": "TBD",
      "figma_current_state_url": "TBD",
      "figma_target_state_url": "TBD",
      "design_system_version": "0.1.0",
      "status": "not_started",
      "priority": "TBD",
      "notes": "TBD"
    }
  ]
}
